pyvista_gui/__init__.py
pyvista_gui/__main__.py
pyvista_gui/_version.py
pyvista_gui/console.py
pyvista_gui/constants.py
pyvista_gui/data.py
pyvista_gui/dialogs.py
pyvista_gui/gui.py
pyvista_gui/options.py
pyvista_gui/utilities.py
pyvista_gui/widgets.py
pyvista_gui-0.1.1.dist-info/LICENSE
pyvista_gui-0.1.1.dist-info/METADATA
pyvista_gui-0.1.1.dist-info/WHEEL
pyvista_gui-0.1.1.dist-info/top_level.txt
pyvista_gui-0.1.1.dist-info/RECORD
