Metadata-Version: 2.1
Name: pyvista-gui
Version: 0.1.1
Summary: Easier Pythonic interface to VTK
Home-page: https://github.com/pyvista/pyvista_gui
Author: PyVista Developers
Author-email: info@pyvista.org
License: MIT
Keywords: vtk numpy plotting mesh gui
Classifier: Development Status :: 4 - Beta
Classifier: Intended Audience :: Science/Research
Classifier: Topic :: Scientific/Engineering :: Information Analysis
Classifier: License :: OSI Approved :: MIT License
Classifier: Operating System :: Microsoft :: Windows
Classifier: Operating System :: POSIX
Classifier: Operating System :: MacOS
Classifier: Programming Language :: Python :: 2.7
Classifier: Programming Language :: Python :: 3.5
Classifier: Programming Language :: Python :: 3.6
Classifier: Programming Language :: Python :: 3.7
Requires-Python: >=2.7,!=3.0.*,!=3.1.*,!=3.2.*,!=3.3.*,!=3.4.*
License-File: LICENSE
Requires-Dist: pyvista (>=0.22.4)
Requires-Dist: PyQt5 (>=5.11.3)
Requires-Dist: scooby (>=0.2.2)
Requires-Dist: matplotlib
Requires-Dist: pyvistaqt
Requires-Dist: qdarkstyle
Requires-Dist: qtconsole
